reporter.py
pytunes_reporter-0.3.2.dist-info/DESCRIPTION.rst
pytunes_reporter-0.3.2.dist-info/METADATA
pytunes_reporter-0.3.2.dist-info/RECORD
pytunes_reporter-0.3.2.dist-info/WHEEL
pytunes_reporter-0.3.2.dist-info/metadata.json
pytunes_reporter-0.3.2.dist-info/top_level.txt
