Metadata-Version: 2.0
Name: pytunes-reporter
Version: 0.3.2
Summary: Library to interact with iTunes Reporter API
Home-page: https://github.com/gifbitjapan/pytunes-reporter
Author: Chason Chaffin
Author-email: chason.c@routeone-power.com
License: UNKNOWN
Keywords: itunes reporter financial sales
Platform: UNKNOWN
Classifier: Development Status :: 3 - Alpha
Classifier: Intended Audience :: Developers
Classifier: Topic :: Software Development :: Libraries
Classifier: Topic :: Office/Business :: Financial
Classifier: License :: OSI Approved :: MIT License
Classifier: Programming Language :: Python :: 3
Classifier: Programming Language :: Python :: 3.6
Requires-Python: >=3.6
Provides-Extra: dev
Provides-Extra: test
Requires-Dist: requests
Provides-Extra: dev
Requires-Dist: bumpversion; extra == 'dev'
Provides-Extra: test
Requires-Dist: pytest (>=3.6); extra == 'test'
Requires-Dist: faker; extra == 'test'
Requires-Dist: responses; extra == 'test'
Requires-Dist: pytest-responses; extra == 'test'
Requires-Dist: coverage; extra == 'test'
Requires-Dist: python-coveralls; extra == 'test'
Requires-Dist: pytest-cov; extra == 'test'
